INSTALL.rst
MANIFEST.in
README.rst
VERSION
setup.py
src/iospec/__init__.py
src/iospec/__meta__.py
src/iospec/errors.py
src/iospec/exceptions.py
src/iospec/feedback.py
src/iospec/parser.py
src/iospec/utils.py
src/iospec.egg-info/PKG-INFO
src/iospec.egg-info/SOURCES.txt
src/iospec.egg-info/dependency_links.txt
src/iospec.egg-info/entry_points.txt
src/iospec.egg-info/not-zip-safe
src/iospec.egg-info/requires.txt
src/iospec.egg-info/top_level.txt
src/iospec/commands/__init__.py
src/iospec/commands/all.py
src/iospec/commands/base.py
src/iospec/commands/utils.py
src/iospec/datatypes/__init__.py
src/iospec/datatypes/atoms.py
src/iospec/datatypes/iospec.py
src/iospec/datatypes/node.py
src/iospec/datatypes/testcases.py
src/iospec/datatypes/utils.py
src/iospec/templates/feedback-div.html
src/iospec/templates/feedback.tex
src/iospec/templates/feedback.txt
src/iospec/tests/__init__.py
src/iospec/tests/__main__.py
src/iospec/tests/test_atoms.py
src/iospec/tests/test_commands.py
src/iospec/tests/test_datatype_utils.py
src/iospec/tests/test_documentation.py
src/iospec/tests/test_exceptions.py
src/iospec/tests/test_feedback.py
src/iospec/tests/test_iospec.py
src/iospec/tests/test_parse_block_types.py
src/iospec/tests/test_parser.py
src/iospec/tests/test_types.py
src/iospec/tests/test_utils.py